seal/__init__.py
seal/main.py
seal/codes/__init__.py
seal/codes/corrector/__init__.py
seal/codes/corrector/base.py
seal/codes/corrector/errors.py
seal/codes/corrector/results.py
seal/codes/corrector/types.py
seal/codes/corrector/strategies/__init__.py
seal/codes/corrector/strategies/default_value_strategy.py
seal/codes/corrector/strategies/fix_prompt_strategy.py
seal/codes/corrector/strategies/type_conversion_strategy.py
seal/codes/engine/__init__.py
seal/codes/engine/errors.py
seal/codes/engine/results.py
seal/codes/engine/seal_engine.py
seal/codes/llm/__init__.py
seal/codes/llm/base.py
seal/codes/llm/errors.py
seal/codes/llm/types.py
seal/codes/llm/adapters/__init__.py
seal/codes/llm/adapters/deepseek.py
seal/codes/parser/__init__.py
seal/codes/parser/errors.py
seal/codes/parser/json_parser.py
seal/codes/prompt/__init__.py
seal/codes/prompt/builder.py
seal/codes/schema/__init__.py
seal/codes/schema/base.py
seal/codes/validation/__init__.py
seal/codes/validation/errors.py
seal/codes/validation/validator.py
seal/demo/quick_start.py
seal_validator-0.1.0.dist-info/licenses/LICENSE
seal_validator-0.1.0.dist-info/METADATA
seal_validator-0.1.0.dist-info/WHEEL
seal_validator-0.1.0.dist-info/top_level.txt
seal_validator-0.1.0.dist-info/RECORD
