Metadata-Version: 2.4
Name: seal-validator
Version: 0.1.0
Summary: A lightweight library for structured output validation in LLM applications
Author-email: Seal Contributors <seal@example.com>
Project-URL: Homepage, https://github.com/yourusername/seal
Project-URL: Documentation, https://github.com/yourusername/seal/wiki
Project-URL: Repository, https://github.com/yourusername/seal.git
Project-URL: Bug Tracker, https://github.com/yourusername/seal/issues
Project-URL: Changelog, https://github.com/yourusername/seal/blob/main/CHANGELOG.md
Keywords: llm,validation,schema,pydantic,structured-output
Classifier: Development Status :: 4 - Beta
Classifier: Intended Audience :: Developers
Classifier: License :: OSI Approved :: MIT License
Classifier: Operating System :: OS Independent
Classifier: Programming Language :: Python :: 3
Classifier: Programming Language :: Python :: 3.8
Classifier: Programming Language :: Python :: 3.9
Classifier: Programming Language :: Python :: 3.10
Classifier: Programming Language :: Python :: 3.11
Classifier: Programming Language :: Python :: 3.12
Classifier: Topic :: Software Development :: Libraries :: Python Modules
Classifier: Topic :: Scientific/Engineering :: Artificial Intelligence
Requires-Python: >=3.8
License-File: LICENSE
Requires-Dist: pydantic>=2.0
Provides-Extra: dev
Requires-Dist: pytest>=7.0; extra == "dev"
Requires-Dist: pytest-cov>=4.0; extra == "dev"
Requires-Dist: black>=22.0; extra == "dev"
Requires-Dist: isort>=5.0; extra == "dev"
Requires-Dist: mypy>=1.0; extra == "dev"
Requires-Dist: ruff>=0.1.0; extra == "dev"
Provides-Extra: llm
Requires-Dist: openai>=1.0; extra == "llm"
Provides-Extra: all
Requires-Dist: openai>=1.0; extra == "all"
Dynamic: license-file
